feathrpiper-0.4.9.dist-info/METADATA
feathrpiper-0.4.9.dist-info/WHEEL
feathrpiper-0.4.9.dist-info/license_files/LICENSE
feathrpiper/__init__.py
feathrpiper/feathrpiper.cpython-311-x86_64-linux-gnu.so
feathrpiper-0.4.9.dist-info/RECORD
