Metadata-Version: 2.1
Name: feathrpiper
Version: 0.4.9
Classifier: Programming Language :: Rust
Classifier: Programming Language :: Python :: Implementation :: CPython
Classifier: Programming Language :: Python :: Implementation :: PyPy
License-File: LICENSE
Home-Page: https://github.com/windoze/piper
Author: Chen Xu <windoze@0d0a.com>
Author-email: Chen Xu <windoze@0d0a.com>
License: MIT
Requires-Python: >=3.7
Project-URL: Source Code, https://github.com/feathr-ai/feathr-online
Project-URL: Issues, https://github.com/feathr-ai/feathr-online/issues
